dsplot/__init__.py
dsplot/config.py
dsplot/errors.py
dsplot/graph/__init__.py
dsplot/graph/graph.py
dsplot/graph/graph_node.py
dsplot/matrix/__init__.py
dsplot/matrix/matrix.py
dsplot/matrix/matrix_node.py
dsplot/node.py
dsplot/tree/__init__.py
dsplot/tree/binary_tree.py
dsplot/tree/tree_node.py
dsplot-0.9.0.dist-info/LICENSE
dsplot-0.9.0.dist-info/WHEEL
dsplot-0.9.0.dist-info/METADATA
dsplot-0.9.0.dist-info/RECORD
