Metadata-Version: 2.1
Name: dsplot
Version: 0.9.0
Summary: Visualize Tree, Graph, and Matrix data structures with ease.
License: MIT
Keywords: Data Structure,Tree,Graph,Matrix,Plot
Author: Bill
Author-email: trantriducs@gmail.com
Requires-Python: >=3.7,<4.0
Classifier: License :: OSI Approved :: MIT License
Classifier: Programming Language :: Python :: 3
Classifier: Programming Language :: Python :: 3.10
Classifier: Programming Language :: Python :: 3.7
Classifier: Programming Language :: Python :: 3.8
Classifier: Programming Language :: Python :: 3.9
Requires-Dist: pygraphviz (>=1.7,<2.0)
